{
  "folding_pathways": [
    {
      "variant_id": "Spike_mRNA_structure_optimized_hairpin_stabilized_optimized_var_1",
      "construct_id": "Spike_mRNA_structure_optimized_hairpin_stabilized_optimized",
      "rna_sequence": "AAGGAGGUCCAAUG",
      "pathway_length": 51,
      "initial_structure": "..............",
      "final_structure": "(.(.....)...).",
      "minimum_energy": -1.5,
      "maximum_energy": 0.6000000000000001,
      "energy_range": 2.1,
      "folding_trajectory": [
        "..............",
        "..............",
        "..............",
        "..............",
        "..............",
        "..............",
        "..............",
        "..............",
        "..............",
        "..............",
        "..............",
        "..............",
        "..............",
        "..............",
        "..............",
        "..............",
        "..............",
        "..............",
        "..............",
        "......(.....)."
      ],
      "energy_trajectory": [
        0.0,
        0.0,
        0.0,
        0.0,
        0.0,
        0.0,
        0.0,
        0.0,
        0.0,
        0.0,
        0.0,
        0.0,
        0.0,
        0.0,
        0.0,
        0.0,
        0.0,
        0.0,
        0.0,
        0.6000000000000001
      ]
    },
    {
      "variant_id": "Spike_mRNA_structure_optimized_hairpin_stabilized_optimized_var_2",
      "construct_id": "Spike_mRNA_structure_optimized_hairpin_stabilized_optimized",
      "rna_sequence": "AGGAGGAAAUAAUG",
      "pathway_length": 51,
      "initial_structure": "..............",
      "final_structure": "..............",
      "minimum_energy": -0.20000000000000018,
      "maximum_energy": 0.0,
      "energy_range": 0.20000000000000018,
      "folding_trajectory": [
        "..............",
        "..............",
        "..............",
        "..............",
        "..............",
        "..............",
        "...(.....)....",
        "..............",
        "..............",
        "..............",
        "..............",
        "..............",
        "..............",
        "..............",
        "..............",
        "..............",
        "..............",
        "..............",
        "..............",
        ".............."
      ],
      "energy_trajectory": [
        0.0,
        0.0,
        0.0,
        0.0,
        0.0,
        0.0,
        -0.10000000000000009,
        0.0,
        0.0,
        0.0,
        0.0,
        0.0,
        0.0,
        0.0,
        0.0,
        0.0,
        0.0,
        0.0,
        0.0,
        0.0
      ]
    },
    {
      "variant_id": "Spike_mRNA_structure_optimized_hairpin_stabilized_optimized_var_3",
      "construct_id": "Spike_mRNA_structure_optimized_hairpin_stabilized_optimized",
      "rna_sequence": "AAGGAGGUAAAGAAUCCAUG",
      "pathway_length": 51,
      "initial_structure": "....................",
      "final_structure": "....................",
      "minimum_energy": -0.20000000000000018,
      "maximum_energy": 0.6000000000000001,
      "energy_range": 0.8000000000000003,
      "folding_trajectory": [
        "....................",
        "....................",
        "....................",
        "....................",
        "....................",
        "....................",
        "....................",
        "....................",
        ".......(....).......",
        ".......(....).......",
        ".......(....).......",
        ".......(....).......",
        ".......(....).......",
        ".......(....).......",
        ".......(....).......",
        ".......(....).......",
        ".......(....).......",
        ".(.....(....).).....",
        ".......(....).......",
        ".......(....)......."
      ],
      "energy_trajectory": [
        0.0,
        0.0,
        0.0,
        0.0,
        0.0,
        0.0,
        0.0,
        0.0,
        -0.10000000000000009,
        -0.10000000000000009,
        -0.10000000000000009,
        -0.10000000000000009,
        -0.10000000000000009,
        -0.10000000000000009,
        -0.10000000000000009,
        -0.10000000000000009,
        -0.10000000000000009,
        -0.20000000000000018,
        -0.10000000000000009,
        -0.10000000000000009
      ]
    },
    {
      "variant_id": "Spike_mRNA_structure_optimized_riboswitch_like_optimized_var_1",
      "construct_id": "Spike_mRNA_structure_optimized_riboswitch_like_optimized",
      "rna_sequence": "AAGGAGGUGGGAAUG",
      "pathway_length": 51,
      "initial_structure": "...............",
      "final_structure": "...............",
      "minimum_energy": -0.10000000000000009,
      "maximum_energy": 0.6000000000000001,
      "energy_range": 0.7000000000000002,
      "folding_trajectory": [
        "...............",
        ".......(....)..",
        ".......(....)..",
        "..(....(....)).",
        "..(....(....)).",
        "..(....(....)).",
        "..(....(....)).",
        "..(....(....)).",
        "..(....(....)).",
        "..(..........).",
        "..(..........).",
        "..(..........).",
        "...............",
        "...............",
        "...............",
        "...............",
        "...............",
        "...............",
        "...............",
        "..............."
      ],
      "energy_trajectory": [
        0.0,
        -0.10000000000000009,
        -0.10000000000000009,
        0.5,
        0.5,
        0.5,
        0.5,
        0.5,
        0.5,
        0.6000000000000001,
        0.6000000000000001,
        0.6000000000000001,
        0.0,
        0.0,
        0.0,
        0.0,
        0.0,
        0.0,
        0.0,
        0.0
      ]
    },
    {
      "variant_id": "Spike_mRNA_structure_optimized_riboswitch_like_optimized_var_2",
      "construct_id": "Spike_mRNA_structure_optimized_riboswitch_like_optimized",
      "rna_sequence": "AGGGAGGCCCAAAUG",
      "pathway_length": 51,
      "initial_structure": "...............",
      "final_structure": "..(......).....",
      "minimum_energy": -1.4,
      "maximum_energy": 0.0,
      "energy_range": 1.4,
      "folding_trajectory": [
        "...............",
        "...............",
        "...............",
        "...............",
        "...............",
        "...............",
        "...............",
        "...............",
        "...............",
        "...(.....).....",
        "...(.....).....",
        "...(.....).....",
        "...(.....).....",
        "...(.....).....",
        "...(.....).....",
        "...(.....).....",
        "...(.....).....",
        "...(.....).....",
        "...(.....).....",
        "..............."
      ],
      "energy_trajectory": [
        0.0,
        0.0,
        0.0,
        0.0,
        0.0,
        0.0,
        0.0,
        0.0,
        0.0,
        -1.4,
        -1.4,
        -1.4,
        -1.4,
        -1.4,
        -1.4,
        -1.4,
        -1.4,
        -1.4,
        -1.4,
        0.0
      ]
    },
    {
      "variant_id": "Spike_mRNA_structure_optimized_riboswitch_like_optimized_var_3",
      "construct_id": "Spike_mRNA_structure_optimized_riboswitch_like_optimized",
      "rna_sequence": "AGGAGGGGGAAGAUG",
      "pathway_length": 51,
      "initial_structure": "...............",
      "final_structure": "...............",
      "minimum_energy": 0.0,
      "maximum_energy": 0.6000000000000001,
      "energy_range": 0.6000000000000001,
      "folding_trajectory": [
        "...............",
        "...............",
        "...............",
        "...............",
        "...............",
        "...............",
        "...............",
        "...............",
        "...............",
        "...............",
        "...............",
        "...............",
        "...............",
        "...............",
        "...............",
        "...............",
        "...............",
        "...............",
        "...............",
        "..............."
      ],
      "energy_trajectory": [
        0.0,
        0.0,
        0.0,
        0.0,
        0.0,
        0.0,
        0.0,
        0.0,
        0.0,
        0.0,
        0.0,
        0.0,
        0.0,
        0.0,
        0.0,
        0.0,
        0.0,
        0.0,
        0.0,
        0.0
      ]
    },
    {
      "variant_id": "Spike_mRNA_structure_optimized_pseudoknot_optimized_var_1",
      "construct_id": "Spike_mRNA_structure_optimized_pseudoknot_optimized",
      "rna_sequence": "AGGAGGUUUAAAAUG",
      "pathway_length": 51,
      "initial_structure": "...............",
      "final_structure": "...............",
      "minimum_energy": -0.10000000000000009,
      "maximum_energy": 0.0,
      "energy_range": 0.10000000000000009,
      "folding_trajectory": [
        "...............",
        ".......(...)...",
        ".......(...)...",
        ".......(...)...",
        ".......(...)...",
        ".......(...)...",
        ".......(...)...",
        "...............",
        "...............",
        "...............",
        "...............",
        "......(.....)..",
        "......(.....)..",
        "......(.....)..",
        "......(.....)..",
        "......(.....)..",
        "......(.....)..",
        "......(.....)..",
        "......(.....)..",
        "......(.....).."
      ],
      "energy_trajectory": [
        0.0,
        -0.10000000000000009,
        -0.10000000000000009,
        -0.10000000000000009,
        -0.10000000000000009,
        -0.10000000000000009,
        -0.10000000000000009,
        0.0,
        0.0,
        0.0,
        0.0,
        -0.10000000000000009,
        -0.10000000000000009,
        -0.10000000000000009,
        -0.10000000000000009,
        -0.10000000000000009,
        -0.10000000000000009,
        -0.10000000000000009,
        -0.10000000000000009,
        -0.10000000000000009
      ]
    },
    {
      "variant_id": "Spike_mRNA_structure_optimized_pseudoknot_optimized_var_2",
      "construct_id": "Spike_mRNA_structure_optimized_pseudoknot_optimized",
      "rna_sequence": "AAGGAGGGGGACAAUG",
      "pathway_length": 51,
      "initial_structure": "................",
      "final_structure": "......(....)....",
      "minimum_energy": -1.4,
      "maximum_energy": 0.6000000000000001,
      "energy_range": 2.0,
      "folding_trajectory": [
        "................",
        "................",
        "......(.......).",
        "......(.......).",
        "......(.......).",
        "......(.......).",
        "......(.......).",
        "................",
        "................",
        "................",
        "................",
        "................",
        "................",
        "................",
        "................",
        "................",
        "................",
        "................",
        "................",
        "................"
      ],
      "energy_trajectory": [
        0.0,
        0.0,
        0.6000000000000001,
        0.6000000000000001,
        0.6000000000000001,
        0.6000000000000001,
        0.6000000000000001,
        0.0,
        0.0,
        0.0,
        0.0,
        0.0,
        0.0,
        0.0,
        0.0,
        0.0,
        0.0,
        0.0,
        0.0,
        0.0
      ]
    },
    {
      "variant_id": "Spike_mRNA_structure_optimized_pseudoknot_optimized_var_3",
      "construct_id": "Spike_mRNA_structure_optimized_pseudoknot_optimized",
      "rna_sequence": "AGGAAGAAGACCAUG",
      "pathway_length": 51,
      "initial_structure": "...............",
      "final_structure": "...............",
      "minimum_energy": -1.4,
      "maximum_energy": 0.0,
      "energy_range": 1.4,
      "folding_trajectory": [
        "...............",
        "...............",
        "...............",
        "....(........).",
        "....(........).",
        "....(........).",
        "....(........).",
        "....(........).",
        "....(........).",
        "....(........).",
        "....(........).",
        "...............",
        "...............",
        "...............",
        "...............",
        "...............",
        "...............",
        "...............",
        "...............",
        "..............."
      ],
      "energy_trajectory": [
        0.0,
        0.0,
        0.0,
        -0.10000000000000009,
        -0.10000000000000009,
        -0.10000000000000009,
        -0.10000000000000009,
        -0.10000000000000009,
        -0.10000000000000009,
        -0.10000000000000009,
        -0.10000000000000009,
        0.0,
        0.0,
        0.0,
        0.0,
        0.0,
        0.0,
        0.0,
        0.0,
        0.0
      ]
    },
    {
      "variant_id": "Spike_mRNA_structure_optimized_kissing_loop_optimized_var_1",
      "construct_id": "Spike_mRNA_structure_optimized_kissing_loop_optimized",
      "rna_sequence": "AGGAAGGAGAAGGCCAAUG",
      "pathway_length": 51,
      "initial_structure": "...................",
      "final_structure": ".....(........)....",
      "minimum_energy": -2.8,
      "maximum_energy": 0.0,
      "energy_range": 2.8,
      "folding_trajectory": [
        "...................",
        "...................",
        "...................",
        "...................",
        "...................",
        "..(..........).....",
        "..(..........).....",
        "..(..........).....",
        "..(..........).....",
        "..(..........).....",
        "..(..........).....",
        "..(..........).....",
        "..(..........).....",
        "..(..........).....",
        "..(..........).....",
        "..(..........).....",
        "..(..........).....",
        "..(..........).....",
        "..(..........).....",
        "..(..........)....."
      ],
      "energy_trajectory": [
        0.0,
        0.0,
        0.0,
        0.0,
        0.0,
        -1.4,
        -1.4,
        -1.4,
        -1.4,
        -1.4,
        -1.4,
        -1.4,
        -1.4,
        -1.4,
        -1.4,
        -1.4,
        -1.4,
        -1.4,
        -1.4,
        -1.4
      ]
    },
    {
      "variant_id": "Spike_mRNA_structure_optimized_kissing_loop_optimized_var_2",
      "construct_id": "Spike_mRNA_structure_optimized_kissing_loop_optimized",
      "rna_sequence": "AAGGAGGGAGUCGAAAAAUG",
      "pathway_length": 51,
      "initial_structure": "....................",
      "final_structure": "...........(.......)",
      "minimum_energy": -1.4,
      "maximum_energy": 0.0,
      "energy_range": 1.4,
      "folding_trajectory": [
        "....................",
        "....................",
        "....................",
        "....................",
        "....................",
        "....................",
        "....................",
        "....................",
        "....................",
        "....................",
        "....................",
        "....................",
        "....................",
        "....................",
        "....................",
        "....................",
        "....................",
        "....................",
        "....................",
        "...................."
      ],
      "energy_trajectory": [
        0.0,
        0.0,
        0.0,
        0.0,
        0.0,
        0.0,
        0.0,
        0.0,
        0.0,
        0.0,
        0.0,
        0.0,
        0.0,
        0.0,
        0.0,
        0.0,
        0.0,
        0.0,
        0.0,
        0.0
      ]
    },
    {
      "variant_id": "Spike_mRNA_structure_optimized_kissing_loop_optimized_var_3",
      "construct_id": "Spike_mRNA_structure_optimized_kissing_loop_optimized",
      "rna_sequence": "AGGAAGAACUUUAUG",
      "pathway_length": 51,
      "initial_structure": "...............",
      "final_structure": "......((..))...",
      "minimum_energy": -0.20000000000000018,
      "maximum_energy": 0.0,
      "energy_range": 0.20000000000000018,
      "folding_trajectory": [
        "...............",
        "...............",
        "......(....)...",
        "......(....)...",
        "...(..(...))...",
        "...(..(...))...",
        "...(.......)...",
        "...(...(...).).",
        "...(...(...).).",
        "...(...(...).).",
        "...(...(...).).",
        "...(...(...).).",
        "...(.........).",
        "...............",
        "...............",
        "...............",
        "...............",
        "...............",
        "...............",
        "..............."
      ],
      "energy_trajectory": [
        0.0,
        0.0,
        -0.10000000000000009,
        -0.10000000000000009,
        -0.20000000000000018,
        -0.20000000000000018,
        -0.10000000000000009,
        -0.20000000000000018,
        -0.20000000000000018,
        -0.20000000000000018,
        -0.20000000000000018,
        -0.20000000000000018,
        -0.10000000000000009,
        0.0,
        0.0,
        0.0,
        0.0,
        0.0,
        0.0,
        0.0
      ]
    }
  ],
  "kinetic_trajectories": [
    {
      "variant_id": "Spike_mRNA_structure_optimized_hairpin_stabilized_optimized_var_1",
      "time_points": [
        0,
        1,
        2,
        3,
        4,
        5,
        6,
        7,
        8,
        9,
        10,
        11,
        12,
        13,
        14,
        15,
        16,
        17,
        18,
        19
      ],
      "structures": [
        "..............",
        "..............",
        "..............",
        "..............",
        "..............",
        "..............",
        "..............",
        "..............",
        "..............",
        "..............",
        "..............",
        "..............",
        "..............",
        "..............",
        "..............",
        "..............",
        "..............",
        "..............",
        "..............",
        "......(.....)."
      ],
      "energies": [
        0.0,
        0.0,
        0.0,
        0.0,
        0.0,
        0.0,
        0.0,
        0.0,
        0.0,
        0.0,
        0.0,
        0.0,
        0.0,
        0.0,
        0.0,
        0.0,
        0.0,
        0.0,
        0.0,
        0.6000000000000001
      ],
      "base_pair_count": [
        0,
        0,
        0,
        0,
        0,
        0,
        0,
        0,
        0,
        0,
        0,
        0,
        0,
        0,
        0,
        0,
        0,
        0,
        0,
        1
      ],
      "compactness": [
        0.0,
        0.0,
        0.0,
        0.0,
        0.0,
        0.0,
        0.0,
        0.0,
        0.0,
        0.0,
        0.0,
        0.0,
        0.0,
        0.0,
        0.0,
        0.0,
        0.0,
        0.0,
        0.0,
        0.14285714285714285
      ],
      "structure_similarity": [
        1.0,
        1.0,
        1.0,
        1.0,
        1.0,
        1.0,
        1.0,
        1.0,
        1.0,
        1.0,
        1.0,
        1.0,
        1.0,
        1.0,
        1.0,
        1.0,
        1.0,
        1.0,
        1.0,
        0.8571428571428571
      ]
    },
    {
      "variant_id": "Spike_mRNA_structure_optimized_hairpin_stabilized_optimized_var_2",
      "time_points": [
        0,
        1,
        2,
        3,
        4,
        5,
        6,
        7,
        8,
        9,
        10,
        11,
        12,
        13,
        14,
        15,
        16,
        17,
        18,
        19
      ],
      "structures": [
        "..............",
        "..............",
        "..............",
        "..............",
        "..............",
        "..............",
        "...(.....)....",
        "..............",
        "..............",
        "..............",
        "..............",
        "..............",
        "..............",
        "..............",
        "..............",
        "..............",
        "..............",
        "..............",
        "..............",
        ".............."
      ],
      "energies": [
        0.0,
        0.0,
        0.0,
        0.0,
        0.0,
        0.0,
        -0.10000000000000009,
        0.0,
        0.0,
        0.0,
        0.0,
        0.0,
        0.0,
        0.0,
        0.0,
        0.0,
        0.0,
        0.0,
        0.0,
        0.0
      ],
      "base_pair_count": [
        0,
        0,
        0,
        0,
        0,
        0,
        1,
        0,
        0,
        0,
        0,
        0,
        0,
        0,
        0,
        0,
        0,
        0,
        0,
        0
      ],
      "compactness": [
        0.0,
        0.0,
        0.0,
        0.0,
        0.0,
        0.0,
        0.14285714285714285,
        0.0,
        0.0,
        0.0,
        0.0,
        0.0,
        0.0,
        0.0,
        0.0,
        0.0,
        0.0,
        0.0,
        0.0,
        0.0
      ],
      "structure_similarity": [
        1.0,
        1.0,
        1.0,
        1.0,
        1.0,
        1.0,
        0.8571428571428571,
        0.8571428571428571,
        1.0,
        1.0,
        1.0,
        1.0,
        1.0,
        1.0,
        1.0,
        1.0,
        1.0,
        1.0,
        1.0,
        1.0
      ]
    },
    {
      "variant_id": "Spike_mRNA_structure_optimized_hairpin_stabilized_optimized_var_3",
      "time_points": [
        0,
        1,
        2,
        3,
        4,
        5,
        6,
        7,
        8,
        9,
        10,
        11,
        12,
        13,
        14,
        15,
        16,
        17,
        18,
        19
      ],
      "structures": [
        "....................",
        "....................",
        "....................",
        "....................",
        "....................",
        "....................",
        "....................",
        "....................",
        ".......(....).......",
        ".......(....).......",
        ".......(....).......",
        ".......(....).......",
        ".......(....).......",
        ".......(....).......",
        ".......(....).......",
        ".......(....).......",
        ".......(....).......",
        ".(.....(....).).....",
        ".......(....).......",
        ".......(....)......."
      ],
      "energies": [
        0.0,
        0.0,
        0.0,
        0.0,
        0.0,
        0.0,
        0.0,
        0.0,
        -0.10000000000000009,
        -0.10000000000000009,
        -0.10000000000000009,
        -0.10000000000000009,
        -0.10000000000000009,
        -0.10000000000000009,
        -0.10000000000000009,
        -0.10000000000000009,
        -0.10000000000000009,
        -0.20000000000000018,
        -0.10000000000000009,
        -0.10000000000000009
      ],
      "base_pair_count": [
        0,
        0,
        0,
        0,
        0,
        0,
        0,
        0,
        1,
        1,
        1,
        1,
        1,
        1,
        1,
        1,
        1,
        2,
        1,
        1
      ],
      "compactness": [
        0.0,
        0.0,
        0.0,
        0.0,
        0.0,
        0.0,
        0.0,
        0.0,
        0.1,
        0.1,
        0.1,
        0.1,
        0.1,
        0.1,
        0.1,
        0.1,
        0.1,
        0.2,
        0.1,
        0.1
      ],
      "structure_similarity": [
        1.0,
        1.0,
        1.0,
        1.0,
        1.0,
        1.0,
        1.0,
        1.0,
        0.9,
        1.0,
        1.0,
        1.0,
        1.0,
        1.0,
        1.0,
        1.0,
        1.0,
        0.9,
        0.9,
        1.0
      ]
    },
    {
      "variant_id": "Spike_mRNA_structure_optimized_riboswitch_like_optimized_var_1",
      "time_points": [
        0,
        1,
        2,
        3,
        4,
        5,
        6,
        7,
        8,
        9,
        10,
        11,
        12,
        13,
        14,
        15,
        16,
        17,
        18,
        19
      ],
      "structures": [
        "...............",
        ".......(....)..",
        ".......(....)..",
        "..(....(....)).",
        "..(....(....)).",
        "..(....(....)).",
        "..(....(....)).",
        "..(....(....)).",
        "..(....(....)).",
        "..(..........).",
        "..(..........).",
        "..(..........).",
        "...............",
        "...............",
        "...............",
        "...............",
        "...............",
        "...............",
        "...............",
        "..............."
      ],
      "energies": [
        0.0,
        -0.10000000000000009,
        -0.10000000000000009,
        0.5,
        0.5,
        0.5,
        0.5,
        0.5,
        0.5,
        0.6000000000000001,
        0.6000000000000001,
        0.6000000000000001,
        0.0,
        0.0,
        0.0,
        0.0,
        0.0,
        0.0,
        0.0,
        0.0
      ],
      "base_pair_count": [
        0,
        1,
        1,
        2,
        2,
        2,
        2,
        2,
        2,
        1,
        1,
        1,
        0,
        0,
        0,
        0,
        0,
        0,
        0,
        0
      ],
      "compactness": [
        0.0,
        0.13333333333333333,
        0.13333333333333333,
        0.26666666666666666,
        0.26666666666666666,
        0.26666666666666666,
        0.26666666666666666,
        0.26666666666666666,
        0.26666666666666666,
        0.13333333333333333,
        0.13333333333333333,
        0.13333333333333333,
        0.0,
        0.0,
        0.0,
        0.0,
        0.0,
        0.0,
        0.0,
        0.0
      ],
      "structure_similarity": [
        1.0,
        0.8666666666666667,
        1.0,
        0.8666666666666667,
        1.0,
        1.0,
        1.0,
        1.0,
        1.0,
        0.8666666666666667,
        1.0,
        1.0,
        0.8666666666666667,
        1.0,
        1.0,
        1.0,
        1.0,
        1.0,
        1.0,
        1.0
      ]
    },
    {
      "variant_id": "Spike_mRNA_structure_optimized_riboswitch_like_optimized_var_2",
      "time_points": [
        0,
        1,
        2,
        3,
        4,
        5,
        6,
        7,
        8,
        9,
        10,
        11,
        12,
        13,
        14,
        15,
        16,
        17,
        18,
        19
      ],
      "structures": [
        "...............",
        "...............",
        "...............",
        "...............",
        "...............",
        "...............",
        "...............",
        "...............",
        "...............",
        "...(.....).....",
        "...(.....).....",
        "...(.....).....",
        "...(.....).....",
        "...(.....).....",
        "...(.....).....",
        "...(.....).....",
        "...(.....).....",
        "...(.....).....",
        "...(.....).....",
        "..............."
      ],
      "energies": [
        0.0,
        0.0,
        0.0,
        0.0,
        0.0,
        0.0,
        0.0,
        0.0,
        0.0,
        -1.4,
        -1.4,
        -1.4,
        -1.4,
        -1.4,
        -1.4,
        -1.4,
        -1.4,
        -1.4,
        -1.4,
        0.0
      ],
      "base_pair_count": [
        0,
        0,
        0,
        0,
        0,
        0,
        0,
        0,
        0,
        1,
        1,
        1,
        1,
        1,
        1,
        1,
        1,
        1,
        1,
        0
      ],
      "compactness": [
        0.0,
        0.0,
        0.0,
        0.0,
        0.0,
        0.0,
        0.0,
        0.0,
        0.0,
        0.13333333333333333,
        0.13333333333333333,
        0.13333333333333333,
        0.13333333333333333,
        0.13333333333333333,
        0.13333333333333333,
        0.13333333333333333,
        0.13333333333333333,
        0.13333333333333333,
        0.13333333333333333,
        0.0
      ],
      "structure_similarity": [
        1.0,
        1.0,
        1.0,
        1.0,
        1.0,
        1.0,
        1.0,
        1.0,
        1.0,
        0.8666666666666667,
        1.0,
        1.0,
        1.0,
        1.0,
        1.0,
        1.0,
        1.0,
        1.0,
        1.0,
        0.8666666666666667
      ]
    },
    {
      "variant_id": "Spike_mRNA_structure_optimized_riboswitch_like_optimized_var_3",
      "time_points": [
        0,
        1,
        2,
        3,
        4,
        5,
        6,
        7,
        8,
        9,
        10,
        11,
        12,
        13,
        14,
        15,
        16,
        17,
        18,
        19
      ],
      "structures": [
        "...............",
        "...............",
        "...............",
        "...............",
        "...............",
        "...............",
        "...............",
        "...............",
        "...............",
        "...............",
        "...............",
        "...............",
        "...............",
        "...............",
        "...............",
        "...............",
        "...............",
        "...............",
        "...............",
        "..............."
      ],
      "energies": [
        0.0,
        0.0,
        0.0,
        0.0,
        0.0,
        0.0,
        0.0,
        0.0,
        0.0,
        0.0,
        0.0,
        0.0,
        0.0,
        0.0,
        0.0,
        0.0,
        0.0,
        0.0,
        0.0,
        0.0
      ],
      "base_pair_count": [
        0,
        0,
        0,
        0,
        0,
        0,
        0,
        0,
        0,
        0,
        0,
        0,
        0,
        0,
        0,
        0,
        0,
        0,
        0,
        0
      ],
      "compactness": [
        0.0,
        0.0,
        0.0,
        0.0,
        0.0,
        0.0,
        0.0,
        0.0,
        0.0,
        0.0,
        0.0,
        0.0,
        0.0,
        0.0,
        0.0,
        0.0,
        0.0,
        0.0,
        0.0,
        0.0
      ],
      "structure_similarity": [
        1.0,
        1.0,
        1.0,
        1.0,
        1.0,
        1.0,
        1.0,
        1.0,
        1.0,
        1.0,
        1.0,
        1.0,
        1.0,
        1.0,
        1.0,
        1.0,
        1.0,
        1.0,
        1.0,
        1.0
      ]
    },
    {
      "variant_id": "Spike_mRNA_structure_optimized_pseudoknot_optimized_var_1",
      "time_points": [
        0,
        1,
        2,
        3,
        4,
        5,
        6,
        7,
        8,
        9,
        10,
        11,
        12,
        13,
        14,
        15,
        16,
        17,
        18,
        19
      ],
      "structures": [
        "...............",
        ".......(...)...",
        ".......(...)...",
        ".......(...)...",
        ".......(...)...",
        ".......(...)...",
        ".......(...)...",
        "...............",
        "...............",
        "...............",
        "...............",
        "......(.....)..",
        "......(.....)..",
        "......(.....)..",
        "......(.....)..",
        "......(.....)..",
        "......(.....)..",
        "......(.....)..",
        "......(.....)..",
        "......(.....).."
      ],
      "energies": [
        0.0,
        -0.10000000000000009,
        -0.10000000000000009,
        -0.10000000000000009,
        -0.10000000000000009,
        -0.10000000000000009,
        -0.10000000000000009,
        0.0,
        0.0,
        0.0,
        0.0,
        -0.10000000000000009,
        -0.10000000000000009,
        -0.10000000000000009,
        -0.10000000000000009,
        -0.10000000000000009,
        -0.10000000000000009,
        -0.10000000000000009,
        -0.10000000000000009,
        -0.10000000000000009
      ],
      "base_pair_count": [
        0,
        1,
        1,
        1,
        1,
        1,
        1,
        0,
        0,
        0,
        0,
        1,
        1,
        1,
        1,
        1,
        1,
        1,
        1,
        1
      ],
      "compactness": [
        0.0,
        0.13333333333333333,
        0.13333333333333333,
        0.13333333333333333,
        0.13333333333333333,
        0.13333333333333333,
        0.13333333333333333,
        0.0,
        0.0,
        0.0,
        0.0,
        0.13333333333333333,
        0.13333333333333333,
        0.13333333333333333,
        0.13333333333333333,
        0.13333333333333333,
        0.13333333333333333,
        0.13333333333333333,
        0.13333333333333333,
        0.13333333333333333
      ],
      "structure_similarity": [
        1.0,
        0.8666666666666667,
        1.0,
        1.0,
        1.0,
        1.0,
        1.0,
        0.8666666666666667,
        1.0,
        1.0,
        1.0,
        0.8666666666666667,
        1.0,
        1.0,
        1.0,
        1.0,
        1.0,
        1.0,
        1.0,
        1.0
      ]
    },
    {
      "variant_id": "Spike_mRNA_structure_optimized_pseudoknot_optimized_var_2",
      "time_points": [
        0,
        1,
        2,
        3,
        4,
        5,
        6,
        7,
        8,
        9,
        10,
        11,
        12,
        13,
        14,
        15,
        16,
        17,
        18,
        19
      ],
      "structures": [
        "................",
        "................",
        "......(.......).",
        "......(.......).",
        "......(.......).",
        "......(.......).",
        "......(.......).",
        "................",
        "................",
        "................",
        "................",
        "................",
        "................",
        "................",
        "................",
        "................",
        "................",
        "................",
        "................",
        "................"
      ],
      "energies": [
        0.0,
        0.0,
        0.6000000000000001,
        0.6000000000000001,
        0.6000000000000001,
        0.6000000000000001,
        0.6000000000000001,
        0.0,
        0.0,
        0.0,
        0.0,
        0.0,
        0.0,
        0.0,
        0.0,
        0.0,
        0.0,
        0.0,
        0.0,
        0.0
      ],
      "base_pair_count": [
        0,
        0,
        1,
        1,
        1,
        1,
        1,
        0,
        0,
        0,
        0,
        0,
        0,
        0,
        0,
        0,
        0,
        0,
        0,
        0
      ],
      "compactness": [
        0.0,
        0.0,
        0.125,
        0.125,
        0.125,
        0.125,
        0.125,
        0.0,
        0.0,
        0.0,
        0.0,
        0.0,
        0.0,
        0.0,
        0.0,
        0.0,
        0.0,
        0.0,
        0.0,
        0.0
      ],
      "structure_similarity": [
        1.0,
        1.0,
        0.875,
        1.0,
        1.0,
        1.0,
        1.0,
        0.875,
        1.0,
        1.0,
        1.0,
        1.0,
        1.0,
        1.0,
        1.0,
        1.0,
        1.0,
        1.0,
        1.0,
        1.0
      ]
    },
    {
      "variant_id": "Spike_mRNA_structure_optimized_pseudoknot_optimized_var_3",
      "time_points": [
        0,
        1,
        2,
        3,
        4,
        5,
        6,
        7,
        8,
        9,
        10,
        11,
        12,
        13,
        14,
        15,
        16,
        17,
        18,
        19
      ],
      "structures": [
        "...............",
        "...............",
        "...............",
        "....(........).",
        "....(........).",
        "....(........).",
        "....(........).",
        "....(........).",
        "....(........).",
        "....(........).",
        "....(........).",
        "...............",
        "...............",
        "...............",
        "...............",
        "...............",
        "...............",
        "...............",
        "...............",
        "..............."
      ],
      "energies": [
        0.0,
        0.0,
        0.0,
        -0.10000000000000009,
        -0.10000000000000009,
        -0.10000000000000009,
        -0.10000000000000009,
        -0.10000000000000009,
        -0.10000000000000009,
        -0.10000000000000009,
        -0.10000000000000009,
        0.0,
        0.0,
        0.0,
        0.0,
        0.0,
        0.0,
        0.0,
        0.0,
        0.0
      ],
      "base_pair_count": [
        0,
        0,
        0,
        1,
        1,
        1,
        1,
        1,
        1,
        1,
        1,
        0,
        0,
        0,
        0,
        0,
        0,
        0,
        0,
        0
      ],
      "compactness": [
        0.0,
        0.0,
        0.0,
        0.13333333333333333,
        0.13333333333333333,
        0.13333333333333333,
        0.13333333333333333,
        0.13333333333333333,
        0.13333333333333333,
        0.13333333333333333,
        0.13333333333333333,
        0.0,
        0.0,
        0.0,
        0.0,
        0.0,
        0.0,
        0.0,
        0.0,
        0.0
      ],
      "structure_similarity": [
        1.0,
        1.0,
        1.0,
        0.8666666666666667,
        1.0,
        1.0,
        1.0,
        1.0,
        1.0,
        1.0,
        1.0,
        0.8666666666666667,
        1.0,
        1.0,
        1.0,
        1.0,
        1.0,
        1.0,
        1.0,
        1.0
      ]
    },
    {
      "variant_id": "Spike_mRNA_structure_optimized_kissing_loop_optimized_var_1",
      "time_points": [
        0,
        1,
        2,
        3,
        4,
        5,
        6,
        7,
        8,
        9,
        10,
        11,
        12,
        13,
        14,
        15,
        16,
        17,
        18,
        19
      ],
      "structures": [
        "...................",
        "...................",
        "...................",
        "...................",
        "...................",
        "..(..........).....",
        "..(..........).....",
        "..(..........).....",
        "..(..........).....",
        "..(..........).....",
        "..(..........).....",
        "..(..........).....",
        "..(..........).....",
        "..(..........).....",
        "..(..........).....",
        "..(..........).....",
        "..(..........).....",
        "..(..........).....",
        "..(..........).....",
        "..(..........)....."
      ],
      "energies": [
        0.0,
        0.0,
        0.0,
        0.0,
        0.0,
        -1.4,
        -1.4,
        -1.4,
        -1.4,
        -1.4,
        -1.4,
        -1.4,
        -1.4,
        -1.4,
        -1.4,
        -1.4,
        -1.4,
        -1.4,
        -1.4,
        -1.4
      ],
      "base_pair_count": [
        0,
        0,
        0,
        0,
        0,
        1,
        1,
        1,
        1,
        1,
        1,
        1,
        1,
        1,
        1,
        1,
        1,
        1,
        1,
        1
      ],
      "compactness": [
        0.0,
        0.0,
        0.0,
        0.0,
        0.0,
        0.10526315789473684,
        0.10526315789473684,
        0.10526315789473684,
        0.10526315789473684,
        0.10526315789473684,
        0.10526315789473684,
        0.10526315789473684,
        0.10526315789473684,
        0.10526315789473684,
        0.10526315789473684,
        0.10526315789473684,
        0.10526315789473684,
        0.10526315789473684,
        0.10526315789473684,
        0.10526315789473684
      ],
      "structure_similarity": [
        1.0,
        1.0,
        1.0,
        1.0,
        1.0,
        0.8947368421052632,
        1.0,
        1.0,
        1.0,
        1.0,
        1.0,
        1.0,
        1.0,
        1.0,
        1.0,
        1.0,
        1.0,
        1.0,
        1.0,
        1.0
      ]
    },
    {
      "variant_id": "Spike_mRNA_structure_optimized_kissing_loop_optimized_var_2",
      "time_points": [
        0,
        1,
        2,
        3,
        4,
        5,
        6,
        7,
        8,
        9,
        10,
        11,
        12,
        13,
        14,
        15,
        16,
        17,
        18,
        19
      ],
      "structures": [
        "....................",
        "....................",
        "....................",
        "....................",
        "....................",
        "....................",
        "....................",
        "....................",
        "....................",
        "....................",
        "....................",
        "....................",
        "....................",
        "....................",
        "....................",
        "....................",
        "....................",
        "....................",
        "....................",
        "...................."
      ],
      "energies": [
        0.0,
        0.0,
        0.0,
        0.0,
        0.0,
        0.0,
        0.0,
        0.0,
        0.0,
        0.0,
        0.0,
        0.0,
        0.0,
        0.0,
        0.0,
        0.0,
        0.0,
        0.0,
        0.0,
        0.0
      ],
      "base_pair_count": [
        0,
        0,
        0,
        0,
        0,
        0,
        0,
        0,
        0,
        0,
        0,
        0,
        0,
        0,
        0,
        0,
        0,
        0,
        0,
        0
      ],
      "compactness": [
        0.0,
        0.0,
        0.0,
        0.0,
        0.0,
        0.0,
        0.0,
        0.0,
        0.0,
        0.0,
        0.0,
        0.0,
        0.0,
        0.0,
        0.0,
        0.0,
        0.0,
        0.0,
        0.0,
        0.0
      ],
      "structure_similarity": [
        1.0,
        1.0,
        1.0,
        1.0,
        1.0,
        1.0,
        1.0,
        1.0,
        1.0,
        1.0,
        1.0,
        1.0,
        1.0,
        1.0,
        1.0,
        1.0,
        1.0,
        1.0,
        1.0,
        1.0
      ]
    },
    {
      "variant_id": "Spike_mRNA_structure_optimized_kissing_loop_optimized_var_3",
      "time_points": [
        0,
        1,
        2,
        3,
        4,
        5,
        6,
        7,
        8,
        9,
        10,
        11,
        12,
        13,
        14,
        15,
        16,
        17,
        18,
        19
      ],
      "structures": [
        "...............",
        "...............",
        "......(....)...",
        "......(....)...",
        "...(..(...))...",
        "...(..(...))...",
        "...(.......)...",
        "...(...(...).).",
        "...(...(...).).",
        "...(...(...).).",
        "...(...(...).).",
        "...(...(...).).",
        "...(.........).",
        "...............",
        "...............",
        "...............",
        "...............",
        "...............",
        "...............",
        "..............."
      ],
      "energies": [
        0.0,
        0.0,
        -0.10000000000000009,
        -0.10000000000000009,
        -0.20000000000000018,
        -0.20000000000000018,
        -0.10000000000000009,
        -0.20000000000000018,
        -0.20000000000000018,
        -0.20000000000000018,
        -0.20000000000000018,
        -0.20000000000000018,
        -0.10000000000000009,
        0.0,
        0.0,
        0.0,
        0.0,
        0.0,
        0.0,
        0.0
      ],
      "base_pair_count": [
        0,
        0,
        1,
        1,
        2,
        2,
        1,
        2,
        2,
        2,
        2,
        2,
        1,
        0,
        0,
        0,
        0,
        0,
        0,
        0
      ],
      "compactness": [
        0.0,
        0.0,
        0.13333333333333333,
        0.13333333333333333,
        0.26666666666666666,
        0.26666666666666666,
        0.13333333333333333,
        0.26666666666666666,
        0.26666666666666666,
        0.26666666666666666,
        0.26666666666666666,
        0.26666666666666666,
        0.13333333333333333,
        0.0,
        0.0,
        0.0,
        0.0,
        0.0,
        0.0,
        0.0
      ],
      "structure_similarity": [
        1.0,
        1.0,
        0.8666666666666667,
        1.0,
        0.8666666666666667,
        1.0,
        0.8666666666666667,
        0.8666666666666667,
        1.0,
        1.0,
        1.0,
        1.0,
        0.8666666666666667,
        0.8666666666666667,
        1.0,
        1.0,
        1.0,
        1.0,
        1.0,
        1.0
      ]
    }
  ],
  "folding_intermediates": [
    {
      "step": 33,
      "structure": "((.....)....).",
      "energy": -0.20000000000000018,
      "stability": 0.10000000000000009,
      "variant_id": "Spike_mRNA_structure_optimized_hairpin_stabilized_optimized_var_1",
      "construct_id": "Spike_mRNA_structure_optimized_hairpin_stabilized_optimized"
    },
    {
      "step": 6,
      "structure": "...(.....)....",
      "energy": -0.10000000000000009,
      "stability": 0.10000000000000009,
      "variant_id": "Spike_mRNA_structure_optimized_hairpin_stabilized_optimized_var_2",
      "construct_id": "Spike_mRNA_structure_optimized_hairpin_stabilized_optimized"
    },
    {
      "step": 17,
      "structure": ".(.....(....).).....",
      "energy": -0.20000000000000018,
      "stability": 0.10000000000000009,
      "variant_id": "Spike_mRNA_structure_optimized_hairpin_stabilized_optimized_var_3",
      "construct_id": "Spike_mRNA_structure_optimized_hairpin_stabilized_optimized"
    },
    {
      "step": 33,
      "structure": ".......(....)..",
      "energy": -0.10000000000000009,
      "stability": 0.10000000000000009,
      "variant_id": "Spike_mRNA_structure_optimized_riboswitch_like_optimized_var_1",
      "construct_id": "Spike_mRNA_structure_optimized_riboswitch_like_optimized"
    },
    {
      "step": 45,
      "structure": ".......(....)..",
      "energy": -0.10000000000000009,
      "stability": 0.10000000000000009,
      "variant_id": "Spike_mRNA_structure_optimized_riboswitch_like_optimized_var_1",
      "construct_id": "Spike_mRNA_structure_optimized_riboswitch_like_optimized"
    },
    {
      "step": 39,
      "structure": "...(...).......",
      "energy": -0.10000000000000009,
      "stability": 0.10000000000000009,
      "variant_id": "Spike_mRNA_structure_optimized_pseudoknot_optimized_var_1",
      "construct_id": "Spike_mRNA_structure_optimized_pseudoknot_optimized"
    },
    {
      "step": 23,
      "structure": "..........(......)..",
      "energy": -0.10000000000000009,
      "stability": 0.10000000000000009,
      "variant_id": "Spike_mRNA_structure_optimized_kissing_loop_optimized_var_2",
      "construct_id": "Spike_mRNA_structure_optimized_kissing_loop_optimized"
    }
  ],
  "energy_landscapes": [
    {
      "variant_id": "Spike_mRNA_structure_optimized_hairpin_stabilized_optimized_var_1",
      "energy_profile": [
        0.0,
        0.0,
        0.0,
        0.0,
        0.0,
        0.0,
        0.0,
        0.0,
        0.0,
        0.0,
        0.0,
        0.0,
        0.0,
        0.0,
        0.0,
        0.0,
        0.0,
        0.0,
        0.0,
        0.6000000000000001
      ],
      "native_energy": -1.5,
      "unfolded_energy": 0.0,
      "folding_funnel_depth": 1.5,
      "energy_roughness": 0.6521428317262514,
      "energy_range": 2.1
    },
    {
      "variant_id": "Spike_mRNA_structure_optimized_hairpin_stabilized_optimized_var_2",
      "energy_profile": [
        0.0,
        0.0,
        0.0,
        0.0,
        0.0,
        0.0,
        -0.10000000000000009,
        0.0,
        0.0,
        0.0,
        0.0,
        0.0,
        0.0,
        0.0,
        0.0,
        0.0,
        0.0,
        0.0,
        0.0,
        0.0
      ],
      "native_energy": -0.20000000000000018,
      "unfolded_energy": 0.0,
      "folding_funnel_depth": 0.20000000000000018,
      "energy_roughness": 0.06341553579920095,
      "energy_range": 0.20000000000000018
    },
    {
      "variant_id": "Spike_mRNA_structure_optimized_hairpin_stabilized_optimized_var_3",
      "energy_profile": [
        0.0,
        0.0,
        0.0,
        0.0,
        0.0,
        0.0,
        0.0,
        0.0,
        -0.10000000000000009,
        -0.10000000000000009,
        -0.10000000000000009,
        -0.10000000000000009,
        -0.10000000000000009,
        -0.10000000000000009,
        -0.10000000000000009,
        -0.10000000000000009,
        -0.10000000000000009,
        -0.20000000000000018,
        -0.10000000000000009,
        -0.10000000000000009
      ],
      "native_energy": -0.20000000000000018,
      "unfolded_energy": 0.0,
      "folding_funnel_depth": 0.20000000000000018,
      "energy_roughness": 0.16209413870933634,
      "energy_range": 0.8000000000000003
    },
    {
      "variant_id": "Spike_mRNA_structure_optimized_riboswitch_like_optimized_var_1",
      "energy_profile": [
        0.0,
        -0.10000000000000009,
        -0.10000000000000009,
        0.5,
        0.5,
        0.5,
        0.5,
        0.5,
        0.5,
        0.6000000000000001,
        0.6000000000000001,
        0.6000000000000001,
        0.0,
        0.0,
        0.0,
        0.0,
        0.0,
        0.0,
        0.0,
        0.0
      ],
      "native_energy": -0.10000000000000009,
      "unfolded_energy": 0.0,
      "folding_funnel_depth": 0.10000000000000009,
      "energy_roughness": 0.22095177015955264,
      "energy_range": 0.7000000000000002
    },
    {
      "variant_id": "Spike_mRNA_structure_optimized_riboswitch_like_optimized_var_2",
      "energy_profile": [
        0.0,
        0.0,
        0.0,
        0.0,
        0.0,
        0.0,
        0.0,
        0.0,
        0.0,
        -1.4,
        -1.4,
        -1.4,
        -1.4,
        -1.4,
        -1.4,
        -1.4,
        -1.4,
        -1.4,
        -1.4,
        0.0
      ],
      "native_energy": -1.4,
      "unfolded_energy": 0.0,
      "folding_funnel_depth": 1.4,
      "energy_roughness": 0.6247736998995082,
      "energy_range": 1.4
    },
    {
      "variant_id": "Spike_mRNA_structure_optimized_riboswitch_like_optimized_var_3",
      "energy_profile": [
        0.0,
        0.0,
        0.0,
        0.0,
        0.0,
        0.0,
        0.0,
        0.0,
        0.0,
        0.0,
        0.0,
        0.0,
        0.0,
        0.0,
        0.0,
        0.0,
        0.0,
        0.0,
        0.0,
        0.0
      ],
      "native_energy": 0.0,
      "unfolded_energy": 0.0,
      "folding_funnel_depth": 0,
      "energy_roughness": 0.16130952000943632,
      "energy_range": 0.6000000000000001
    },
    {
      "variant_id": "Spike_mRNA_structure_optimized_pseudoknot_optimized_var_1",
      "energy_profile": [
        0.0,
        -0.10000000000000009,
        -0.10000000000000009,
        -0.10000000000000009,
        -0.10000000000000009,
        -0.10000000000000009,
        -0.10000000000000009,
        0.0,
        0.0,
        0.0,
        0.0,
        -0.10000000000000009,
        -0.10000000000000009,
        -0.10000000000000009,
        -0.10000000000000009,
        -0.10000000000000009,
        -0.10000000000000009,
        -0.10000000000000009,
        -0.10000000000000009,
        -0.10000000000000009
      ],
      "native_energy": -0.10000000000000009,
      "unfolded_energy": 0.0,
      "folding_funnel_depth": 0.10000000000000009,
      "energy_roughness": 0.049913419848462225,
      "energy_range": 0.10000000000000009
    },
    {
      "variant_id": "Spike_mRNA_structure_optimized_pseudoknot_optimized_var_2",
      "energy_profile": [
        0.0,
        0.0,
        0.6000000000000001,
        0.6000000000000001,
        0.6000000000000001,
        0.6000000000000001,
        0.6000000000000001,
        0.0,
        0.0,
        0.0,
        0.0,
        0.0,
        0.0,
        0.0,
        0.0,
        0.0,
        0.0,
        0.0,
        0.0,
        0.0
      ],
      "native_energy": -1.4,
      "unfolded_energy": 0.0,
      "folding_funnel_depth": 1.4,
      "energy_roughness": 0.6678881543323134,
      "energy_range": 2.0
    },
    {
      "variant_id": "Spike_mRNA_structure_optimized_pseudoknot_optimized_var_3",
      "energy_profile": [
        0.0,
        0.0,
        0.0,
        -0.10000000000000009,
        -0.10000000000000009,
        -0.10000000000000009,
        -0.10000000000000009,
        -0.10000000000000009,
        -0.10000000000000009,
        -0.10000000000000009,
        -0.10000000000000009,
        0.0,
        0.0,
        0.0,
        0.0,
        0.0,
        0.0,
        0.0,
        0.0,
        0.0
      ],
      "native_energy": -1.4,
      "unfolded_energy": 0.0,
      "folding_funnel_depth": 1.4,
      "energy_roughness": 0.6832313480594732,
      "energy_range": 1.4
    },
    {
      "variant_id": "Spike_mRNA_structure_optimized_kissing_loop_optimized_var_1",
      "energy_profile": [
        0.0,
        0.0,
        0.0,
        0.0,
        0.0,
        -1.4,
        -1.4,
        -1.4,
        -1.4,
        -1.4,
        -1.4,
        -1.4,
        -1.4,
        -1.4,
        -1.4,
        -1.4,
        -1.4,
        -1.4,
        -1.4,
        -1.4
      ],
      "native_energy": -2.8,
      "unfolded_energy": 0.0,
      "folding_funnel_depth": 2.8,
      "energy_roughness": 0.6355361436826006,
      "energy_range": 2.8
    },
    {
      "variant_id": "Spike_mRNA_structure_optimized_kissing_loop_optimized_var_2",
      "energy_profile": [
        0.0,
        0.0,
        0.0,
        0.0,
        0.0,
        0.0,
        0.0,
        0.0,
        0.0,
        0.0,
        0.0,
        0.0,
        0.0,
        0.0,
        0.0,
        0.0,
        0.0,
        0.0,
        0.0,
        0.0
      ],
      "native_energy": -1.4,
      "unfolded_energy": 0.0,
      "folding_funnel_depth": 1.4,
      "energy_roughness": 0.4145934580843641,
      "energy_range": 1.4
    },
    {
      "variant_id": "Spike_mRNA_structure_optimized_kissing_loop_optimized_var_3",
      "energy_profile": [
        0.0,
        0.0,
        -0.10000000000000009,
        -0.10000000000000009,
        -0.20000000000000018,
        -0.20000000000000018,
        -0.10000000000000009,
        -0.20000000000000018,
        -0.20000000000000018,
        -0.20000000000000018,
        -0.20000000000000018,
        -0.20000000000000018,
        -0.10000000000000009,
        0.0,
        0.0,
        0.0,
        0.0,
        0.0,
        0.0,
        0.0
      ],
      "native_energy": -0.20000000000000018,
      "unfolded_energy": 0.0,
      "folding_funnel_depth": 0.20000000000000018,
      "energy_roughness": 0.07984028655491117,
      "energy_range": 0.20000000000000018
    }
  ],
  "transition_states": [],
  "folding_kinetics": [
    {
      "variant_id": "Spike_mRNA_structure_optimized_hairpin_stabilized_optimized_var_1",
      "folding_rate": 810584.2459701871,
      "unfolding_rate": 740.8182206817179,
      "equilibrium_constant": 1094.1742837052104,
      "folding_half_life": 8.54938895550023e-07,
      "unfolding_half_life": 0.0009354521536501701,
      "cooperativity": 1,
      "folding_time_scale": "milliseconds"
    },
    {
      "variant_id": "Spike_mRNA_structure_optimized_hairpin_stabilized_optimized_var_2",
      "folding_rate": 980198.6733067553,
      "unfolding_rate": 960.7894391523232,
      "equilibrium_constant": 1020.2013400267558,
      "folding_half_life": 7.069995286385418e-07,
      "unfolding_half_life": 0.000721281866515325,
      "cooperativity": 1,
      "folding_time_scale": "milliseconds"
    },
    {
      "variant_id": "Spike_mRNA_structure_optimized_hairpin_stabilized_optimized_var_3",
      "folding_rate": 923116.3463866358,
      "unfolding_rate": 960.7894391523232,
      "equilibrium_constant": 960.7894391523232,
      "folding_half_life": 7.507179378987462e-07,
      "unfolding_half_life": 0.000721281866515325,
      "cooperativity": 1,
      "folding_time_scale": "milliseconds"
    },
    {
      "variant_id": "Spike_mRNA_structure_optimized_riboswitch_like_optimized_var_1",
      "folding_rate": 932393.8199059481,
      "unfolding_rate": 980.1986733067553,
      "equilibrium_constant": 951.2294245007139,
      "folding_half_life": 7.432481696091721e-07,
      "unfolding_half_life": 0.0007069995286385417,
      "cooperativity": 2,
      "folding_time_scale": "milliseconds"
    },
    {
      "variant_id": "Spike_mRNA_structure_optimized_riboswitch_like_optimized_var_2",
      "folding_rate": 869358.2353988058,
      "unfolding_rate": 755.7837414557255,
      "equilibrium_constant": 1150.2737988572273,
      "folding_half_life": 7.971397426080584e-07,
      "unfolding_half_life": 0.0009169289599498437,
      "cooperativity": 0,
      "folding_time_scale": "milliseconds"
    },
    {
      "variant_id": "Spike_mRNA_structure_optimized_riboswitch_like_optimized_var_3",
      "folding_rate": 941764.5335842487,
      "unfolding_rate": 1000.0,
      "equilibrium_constant": 941.7645335842487,
      "folding_half_life": 7.358527267559342e-07,
      "unfolding_half_life": 0.0006929999999999999,
      "cooperativity": 0,
      "folding_time_scale": "milliseconds"
    },
    {
      "variant_id": "Spike_mRNA_structure_optimized_pseudoknot_optimized_var_1",
      "folding_rate": 990049.833749168,
      "unfolding_rate": 980.1986733067553,
      "equilibrium_constant": 1010.050167084168,
      "folding_half_life": 6.999647657893285e-07,
      "unfolding_half_life": 0.0007069995286385417,
      "cooperativity": 1,
      "folding_time_scale": "milliseconds"
    },
    {
      "variant_id": "Spike_mRNA_structure_optimized_pseudoknot_optimized_var_2",
      "folding_rate": 818730.7530779819,
      "unfolding_rate": 755.7837414557255,
      "equilibrium_constant": 1083.2870676749585,
      "folding_half_life": 8.464321114049977e-07,
      "unfolding_half_life": 0.0009169289599498437,
      "cooperativity": 0,
      "folding_time_scale": "milliseconds"
    },
    {
      "variant_id": "Spike_mRNA_structure_optimized_pseudoknot_optimized_var_3",
      "folding_rate": 869358.2353988058,
      "unfolding_rate": 755.7837414557255,
      "equilibrium_constant": 1150.2737988572273,
      "folding_half_life": 7.971397426080584e-07,
      "unfolding_half_life": 0.0009169289599498437,
      "cooperativity": 0,
      "folding_time_scale": "milliseconds"
    },
    {
      "variant_id": "Spike_mRNA_structure_optimized_kissing_loop_optimized_var_1",
      "folding_rate": 755783.7414557255,
      "unfolding_rate": 571.2090638488148,
      "equilibrium_constant": 1323.1298123374372,
      "folding_half_life": 9.169289599498437e-07,
      "unfolding_half_life": 0.0012132160427051981,
      "cooperativity": 0,
      "folding_time_scale": "milliseconds"
    },
    {
      "variant_id": "Spike_mRNA_structure_optimized_kissing_loop_optimized_var_2",
      "folding_rate": 869358.2353988058,
      "unfolding_rate": 755.7837414557255,
      "equilibrium_constant": 1150.2737988572273,
      "folding_half_life": 7.971397426080584e-07,
      "unfolding_half_life": 0.0009169289599498437,
      "cooperativity": 1,
      "folding_time_scale": "milliseconds"
    },
    {
      "variant_id": "Spike_mRNA_structure_optimized_kissing_loop_optimized_var_3",
      "folding_rate": 980198.6733067553,
      "unfolding_rate": 960.7894391523232,
      "equilibrium_constant": 1020.2013400267558,
      "folding_half_life": 7.069995286385418e-07,
      "unfolding_half_life": 0.000721281866515325,
      "cooperativity": 0,
      "folding_time_scale": "milliseconds"
    }
  ],
  "structural_dynamics": [
    {
      "variant_id": "Spike_mRNA_structure_optimized_hairpin_stabilized_optimized_var_1",
      "average_base_pairs": 0.7647058823529411,
      "max_base_pairs": 2,
      "average_compactness": 0.10924369747899157,
      "structure_fluctuation": 0.04602710567270305,
      "folding_cooperativity": 8.678966994124725
    },
    {
      "variant_id": "Spike_mRNA_structure_optimized_hairpin_stabilized_optimized_var_2",
      "average_base_pairs": 0.43137254901960786,
      "max_base_pairs": 2,
      "average_compactness": 0.06162464985994397,
      "structure_fluctuation": 0.04602710567270305,
      "folding_cooperativity": 11.038304591740449
    },
    {
      "variant_id": "Spike_mRNA_structure_optimized_hairpin_stabilized_optimized_var_3",
      "average_base_pairs": 0.5490196078431373,
      "max_base_pairs": 2,
      "average_compactness": 0.05490196078431373,
      "structure_fluctuation": 0.0363671313548851,
      "folding_cooperativity": 15.723973607444286
    },
    {
      "variant_id": "Spike_mRNA_structure_optimized_riboswitch_like_optimized_var_1",
      "average_base_pairs": 0.39215686274509803,
      "max_base_pairs": 2,
      "average_compactness": 0.052287581699346414,
      "structure_fluctuation": 0.05293714178121982,
      "folding_cooperativity": 10.89748012395288
    },
    {
      "variant_id": "Spike_mRNA_structure_optimized_riboswitch_like_optimized_var_2",
      "average_base_pairs": 0.7254901960784313,
      "max_base_pairs": 1,
      "average_compactness": 0.09673202614379087,
      "structure_fluctuation": 0.03137254901960783,
      "folding_cooperativity": 16.806085150013317
    },
    {
      "variant_id": "Spike_mRNA_structure_optimized_riboswitch_like_optimized_var_3",
      "average_base_pairs": 0.0784313725490196,
      "max_base_pairs": 1,
      "average_compactness": 0.01045751633986928,
      "structure_fluctuation": 0.025881032514017417,
      "folding_cooperativity": 27.896679623972336
    },
    {
      "variant_id": "Spike_mRNA_structure_optimized_pseudoknot_optimized_var_1",
      "average_base_pairs": 0.47058823529411764,
      "max_base_pairs": 1,
      "average_compactness": 0.06274509803921569,
      "structure_fluctuation": 0.05655766706610178,
      "folding_cooperativity": 15.026019100214134
    },
    {
      "variant_id": "Spike_mRNA_structure_optimized_pseudoknot_optimized_var_2",
      "average_base_pairs": 0.35294117647058826,
      "max_base_pairs": 1,
      "average_compactness": 0.04411764705882353,
      "structure_fluctuation": 0.03717095805907623,
      "folding_cooperativity": 16.74044277318925
    },
    {
      "variant_id": "Spike_mRNA_structure_optimized_pseudoknot_optimized_var_3",
      "average_base_pairs": 0.6078431372549019,
      "max_base_pairs": 1,
      "average_compactness": 0.08104575163398692,
      "structure_fluctuation": 0.035846560002096954,
      "folding_cooperativity": 15.36156966526029
    },
    {
      "variant_id": "Spike_mRNA_structure_optimized_kissing_loop_optimized_var_1",
      "average_base_pairs": 0.9019607843137255,
      "max_base_pairs": 2,
      "average_compactness": 0.09494324045407639,
      "structure_fluctuation": 0.03130185941816946,
      "folding_cooperativity": 20.92721260970845
    },
    {
      "variant_id": "Spike_mRNA_structure_optimized_kissing_loop_optimized_var_2",
      "average_base_pairs": 0.17647058823529413,
      "max_base_pairs": 1,
      "average_compactness": 0.01764705882352941,
      "structure_fluctuation": 0.02973676644726098,
      "folding_cooperativity": 26.23156949355562
    },
    {
      "variant_id": "Spike_mRNA_structure_optimized_kissing_loop_optimized_var_3",
      "average_base_pairs": 1.0980392156862746,
      "max_base_pairs": 2,
      "average_compactness": 0.14640522875816994,
      "structure_fluctuation": 0.05293714178121982,
      "folding_cooperativity": 9.393753859891003
    }
  ],
  "pathway_analysis": [
    {
      "variant_id": "Spike_mRNA_structure_optimized_hairpin_stabilized_optimized_var_1",
      "folding_mechanism": "two_state",
      "dominant_interactions": "base_pairing",
      "folding_nucleus_size": 1,
      "pathway_diversity": 1,
      "thermodynamic_stability": 1.5
    },
    {
      "variant_id": "Spike_mRNA_structure_optimized_hairpin_stabilized_optimized_var_2",
      "folding_mechanism": "two_state",
      "dominant_interactions": "base_pairing",
      "folding_nucleus_size": 1,
      "pathway_diversity": 2,
      "thermodynamic_stability": 0.20000000000000018
    },
    {
      "variant_id": "Spike_mRNA_structure_optimized_hairpin_stabilized_optimized_var_3",
      "folding_mechanism": "two_state",
      "dominant_interactions": "base_pairing",
      "folding_nucleus_size": 1,
      "pathway_diversity": 2,
      "thermodynamic_stability": 0.20000000000000018
    },
    {
      "variant_id": "Spike_mRNA_structure_optimized_riboswitch_like_optimized_var_1",
      "folding_mechanism": "two_state",
      "dominant_interactions": "base_pairing",
      "folding_nucleus_size": 1,
      "pathway_diversity": 4,
      "thermodynamic_stability": 0.10000000000000009
    },
    {
      "variant_id": "Spike_mRNA_structure_optimized_riboswitch_like_optimized_var_2",
      "folding_mechanism": "two_state",
      "dominant_interactions": "base_pairing",
      "folding_nucleus_size": 0,
      "pathway_diversity": 2,
      "thermodynamic_stability": 1.4
    },
    {
      "variant_id": "Spike_mRNA_structure_optimized_riboswitch_like_optimized_var_3",
      "folding_mechanism": "two_state",
      "dominant_interactions": "base_pairing",
      "folding_nucleus_size": 0,
      "pathway_diversity": 1,
      "thermodynamic_stability": 0.0
    },
    {
      "variant_id": "Spike_mRNA_structure_optimized_pseudoknot_optimized_var_1",
      "folding_mechanism": "two_state",
      "dominant_interactions": "base_pairing",
      "folding_nucleus_size": 0,
      "pathway_diversity": 2,
      "thermodynamic_stability": 0.10000000000000009
    },
    {
      "variant_id": "Spike_mRNA_structure_optimized_pseudoknot_optimized_var_2",
      "folding_mechanism": "two_state",
      "dominant_interactions": "base_pairing",
      "folding_nucleus_size": 0,
      "pathway_diversity": 2,
      "thermodynamic_stability": 1.4
    },
    {
      "variant_id": "Spike_mRNA_structure_optimized_pseudoknot_optimized_var_3",
      "folding_mechanism": "two_state",
      "dominant_interactions": "base_pairing",
      "folding_nucleus_size": 0,
      "pathway_diversity": 2,
      "thermodynamic_stability": 1.4
    },
    {
      "variant_id": "Spike_mRNA_structure_optimized_kissing_loop_optimized_var_1",
      "folding_mechanism": "two_state",
      "dominant_interactions": "base_pairing",
      "folding_nucleus_size": 1,
      "pathway_diversity": 2,
      "thermodynamic_stability": 2.8
    },
    {
      "variant_id": "Spike_mRNA_structure_optimized_kissing_loop_optimized_var_2",
      "folding_mechanism": "two_state",
      "dominant_interactions": "base_pairing",
      "folding_nucleus_size": 0,
      "pathway_diversity": 1,
      "thermodynamic_stability": 1.4
    },
    {
      "variant_id": "Spike_mRNA_structure_optimized_kissing_loop_optimized_var_3",
      "folding_mechanism": "two_state",
      "dominant_interactions": "base_pairing",
      "folding_nucleus_size": 1,
      "pathway_diversity": 5,
      "thermodynamic_stability": 0.20000000000000018
    }
  ],
  "folding_rates": {
    "average_folding_rate": 895074.6105783187,
    "average_unfolding_rate": 848.1606595353263,
    "rate_distribution": [
      810584.2459701871,
      980198.6733067553,
      923116.3463866358,
      932393.8199059481,
      869358.2353988058,
      941764.5335842487,
      990049.833749168,
      818730.7530779819,
      869358.2353988058,
      755783.7414557255,
      869358.2353988058,
      980198.6733067553
    ],
    "fast_folders": 0,
    "slow_folders": 0,
    "rate_range": [
      755783.7414557255,
      990049.833749168
    ]
  },
  "stability_metrics": {
    "sequences_analyzed": 12,
    "total_pathways": 12,
    "average_energy_range": 1.1416666666666668,
    "average_folding_depth": 0.8916666666666669,
    "stable_intermediates": 0,
    "cooperative_folders": 12,
    "average_compactness": 0.06934595475617149
  },
  "metadata": {
    "tool": "KineFold",
    "operation": "rna_kinetic_folding_analysis",
    "sequences_processed": 4,
    "pathways_simulated": 12,
    "simulation_steps": 50,
    "temperature": 37.0,
    "analysis_complete": true
  }
}